{
  "entityType" : "DEVICE",
  "entity" : {
    "additionalInfo" : {
      "gateway" : false,
      "overwriteActivityTime" : false,
      "description" : ""
    },
    "customerId" : {
      "entityType" : "CUSTOMER",
      "id" : "13814000-1dd2-11b2-8080-808080808080"
    },
    "deviceData" : {
      "configuration" : {
        "type" : "DEFAULT"
      },
      "transportConfiguration" : {
        "type" : "DEFAULT"
      }
    },
    "deviceProfileId" : {
      "entityType" : "DEVICE_PROFILE",
      "id" : "5e9235a0-bfcb-11ed-aac5-8fafa8b142a8"
    },
    "externalId" : null,
    "firmwareId" : null,
    "id" : {
      "entityType" : "DEVICE",
      "id" : "62cbc1d0-c256-11ed-a7d5-7130de4f66b9"
    },
    "label" : "",
    "name" : "thermostat-1",
    "softwareId" : null,
    "type" : "default"
  },
  "credentials" : {
    "credentialsId" : "cja6cykX37oAS3qhvcK1",
    "credentialsType" : "ACCESS_TOKEN",
    "credentialsValue" : null
  },
  "attributes" : {
    "SERVER_SCOPE" : [ {
      "booleanValue" : false,
      "doubleValue" : null,
      "jsonValue" : null,
      "key" : "active",
      "lastUpdateTs" : 1678795194857,
      "longValue" : null,
      "strValue" : null
    }, {
      "booleanValue" : null,
      "doubleValue" : null,
      "jsonValue" : null,
      "key" : "inactivityAlarmTime",
      "lastUpdateTs" : 1678795194871,
      "longValue" : 1678795194855,
      "strValue" : null
    }, {
      "booleanValue" : null,
      "doubleValue" : null,
      "jsonValue" : null,
      "key" : "lastActivityTime",
      "lastUpdateTs" : 1678794405191,
      "longValue" : 1678794403909,
      "strValue" : null
    } ],
    "SHARED_SCOPE" : [ ]
  }
}